doctr_synth_generator-0.0.1.dist-info/licenses/LICENSE
generator/__init__.py
generator/dataset_generator.py
generator/py.typed
generator/version.py
generator/augmentations/__init__.py
generator/augmentations/augmentation_pipeline.py
generator/augmentations/random_blur.py
generator/augmentations/random_perspective.py
generator/augmentations/random_rotate.py
generator/components/__init__.py
generator/components/background_manager.py
generator/components/config.py
generator/components/dataset_splitter.py
generator/components/font_selector.py
generator/components/generator.py
generator/components/text_renderer.py
generator/components/vocabs.py
doctr_synth_generator-0.0.1.dist-info/METADATA
doctr_synth_generator-0.0.1.dist-info/WHEEL
doctr_synth_generator-0.0.1.dist-info/top_level.txt
doctr_synth_generator-0.0.1.dist-info/zip-safe
doctr_synth_generator-0.0.1.dist-info/RECORD
