Metadata-Version: 2.4
Name: doctr-synth-generator
Version: 0.0.1
Summary: A synthetic data generator for training OCR models
Author-email: Felix Dittrich <felixdittrich92@gmail.com>
Maintainer: Felix Dittrich
License:                                  Apache License
Project-URL: repository, https://github.com/felixdittrich92/docTR-Synth-Generator
Project-URL: tracker, https://github.com/felixdittrich92/docTR-Synth-Generator/issues
Project-URL: changelog, https://github.com/felixdittrich92/docTR-Synth-Generator/releases
Keywords: OCR,deep learning,computer vision,text recognition,synthetic data,data augmentation,image processing
Classifier: Development Status :: 4 - Beta
Classifier: Intended Audience :: Developers
Classifier: Intended Audience :: Education
Classifier: Intended Audience :: Science/Research
Classifier: License :: OSI Approved :: Apache Software License
Classifier: Natural Language :: English
Classifier: Operating System :: OS Independent
Classifier: Programming Language :: Python :: 3
Classifier: Programming Language :: Python :: 3.10
Classifier: Programming Language :: Python :: 3.11
Classifier: Programming Language :: Python :: 3.12
Classifier: Topic :: Scientific/Engineering :: Artificial Intelligence
Requires-Python: <4,>=3.10.0
License-File: LICENSE
Requires-Dist: fonttools<5.0.0,>=4.50.0
Requires-Dist: numpy<3.0.0,>=2.0.0
Requires-Dist: Pillow>=11.0.0
Provides-Extra: testing
Requires-Dist: pytest>=5.3.2; extra == "testing"
Requires-Dist: coverage[toml]>=4.5.4; extra == "testing"
Provides-Extra: quality
Requires-Dist: ruff>=0.1.5; extra == "quality"
Requires-Dist: mypy>=0.812; extra == "quality"
Requires-Dist: pre-commit>=2.17.0; extra == "quality"
Provides-Extra: dev
Requires-Dist: fonttools<5.0.0,>=4.50.0; extra == "dev"
Requires-Dist: numpy<3.0.0,>=2.0.0; extra == "dev"
Requires-Dist: Pillow>=11.0.0; extra == "dev"
Requires-Dist: pytest>=5.3.2; extra == "dev"
Requires-Dist: coverage[toml]>=4.5.4; extra == "dev"
Requires-Dist: ruff>=0.1.5; extra == "dev"
Requires-Dist: mypy>=0.812; extra == "dev"
Requires-Dist: pre-commit>=2.17.0; extra == "dev"
Dynamic: license-file
